{"cameraMode":{"drawMode":0,"name":"Shaded","section":"Shading Mode"},"sceneLighting":true,"audioPlay":false,"sceneViewState":{"m_AlwaysRefresh":false,"showFog":true,"showSkybox":true,"showFlares":true,"showImageEffects":true,"showParticleSystems":true,"showVisualEffectGraphs":true,"m_FxEnabled":true},"in2DMode":false,"pivot":{"x":9.192924499511719,"y":1.8886338472366334,"z":8.932092666625977},"rotation":{"x":0.12280067801475525,"y":0.05833347886800766,"z":-0.007155461236834526,"w":0.9907733201980591},"size":10.0,"orthographic":false}